{
  "/assets/css/style-pl.css": "725f40f3",
  "/assets/css/style-base.css": "93a3f518",
  "/assets/css/p-root.css": "dabc078b",
  "/assets/css/b-teaser.css": "235d6937",
  "/assets/css/b-root.css": "a7fbd5b7",
  "/assets/css/b-people.css": "dc35e7fb",
  "/assets/css/b-partner.css": "38fcff48",
  "/assets/css/b-hero.css": "434b743c",
  "/assets/css/b-header.css": "bff72827",
  "/assets/css/b-footer.css": "485b45ac",
  "/assets/images/root.svg": "d95e65b7",
  "/assets/images/logo.svg": "765e389e",
  "/assets/images/icons.svg": "8a8a8b50",
  "/assets/js/vendor.0x2c817467.js": "",
  "/assets/js/root.js": "eab4a04c",
  "/assets/js/root.0xbc6f3915.js": "",
  "/assets/js/require-css.0x66d2cab8.js": "",
  "/assets/js/react-loader.0x12535d34.js": "",
  "/assets/js/pl-states.js": "41e18f29",
  "/assets/js/people.0x0d254119.js": "",
  "/assets/js/main.js": "dee210f1",
  "/assets/js/header.js": "1229a389"
}